pokerl/__init__.py
pokerl/cards.py
pokerl/enums.py
pokerl/game.py
pokerl/judger.py
pokerl/agents/__init__.py
pokerl/agents/agent.py
pokerl/agents/human.py
pokerl/agents/random.py
pokerl/envs/__init__.py
pokerl/envs/env.py
pokerl/envs/game_env.py
pokerl/network/__init__.py
pokerl/network/client.py
pokerl/network/server.py
pokerl-0.0.6.dist-info/LICENSE
pokerl-0.0.6.dist-info/METADATA
pokerl-0.0.6.dist-info/WHEEL
pokerl-0.0.6.dist-info/top_level.txt
pokerl-0.0.6.dist-info/RECORD
