Metadata-Version: 2.1
Name: pokerl
Version: 0.0.6
Summary: RL environments for poker games
Home-page: https://github.com/sneppy/pokerl
Author: ('Andrea Mecchia, Guglielmo Manneschi',)
Author-email: mecchia.andrea@gmail.com
License: MIT
Platform: UNKNOWN
Classifier: Development Status :: 1 - Planning
Classifier: Operating System :: OS Independent
Classifier: Programming Language :: Python :: 3.6
Classifier: Programming Language :: Python :: 3.7
Classifier: Programming Language :: Python :: 3.8
Classifier: Programming Language :: Python :: 3.9
Classifier: Topic :: Scientific/Engineering :: Artificial Intelligence
Classifier: Intended Audience :: Science/Research
Classifier: License :: OSI Approved :: MIT License
Classifier: Natural Language :: English
Requires-Python: >=3.6
Requires-Dist: numpy (>=1.18.0)
